LICENSE.txt
README.md
setup.py
beuty_print.egg-info/PKG-INFO
beuty_print.egg-info/SOURCES.txt
beuty_print.egg-info/dependency_links.txt
beuty_print.egg-info/requires.txt
beuty_print.egg-info/top_level.txt
beutyprint/__init__.py