Metadata-Version: 2.1
Name: beuty-print
Version: 1.0.5
Summary: Just a simple library to print your script outputs in more neat / colorful way without much overhead
Author: Hex24 (Markas Vielavičius)
Author-email: <markas.vielavicius@gmail.com>
Keywords: python,printer,print,color,simple,format
Classifier: Development Status :: 1 - Planning
Classifier: Intended Audience :: Developers
Classifier: Programming Language :: Python :: 3
Classifier: Operating System :: Unix
Classifier: Operating System :: MacOS :: MacOS X
Classifier: Operating System :: Microsoft :: Windows
License-File: LICENSE.txt
